ilt_py_lib-1.0.0.dist-info/licenses/CITATION.cff
ilt_py_lib-1.0.0.dist-info/licenses/COPYING.LESSER.txt
ilt_py_lib-1.0.0.dist-info/licenses/COPYING.txt
ilt_py_lib-1.0.0.dist-info/licenses/LICENSE
iltpy/__init__.py
iltpy/fit/__init__.py
iltpy/fit/inversion.py
iltpy/fit/kernels.py
iltpy/fit/regularization.py
iltpy/input/__init__.py
iltpy/input/loader.py
iltpy/input/parameters.py
iltpy/output/__init__.py
iltpy/output/plotting.py
iltpy/output/reporting.py
iltpy/utils/__init__.py
iltpy/utils/scripts.py
ilt_py_lib-1.0.0.dist-info/METADATA
ilt_py_lib-1.0.0.dist-info/WHEEL
ilt_py_lib-1.0.0.dist-info/top_level.txt
ilt_py_lib-1.0.0.dist-info/RECORD
