Metadata-Version: 2.4
Name: ilt-py-lib
Version: 1.0.0
Summary: A python library for inverse Laplace transform of one dimensional and multidimensional data.
Home-page: https://apps.fz-juelich.de/iltpy
Author: Davis Thomas Daniel, Josef Granwehr
Author-email: Davis Thomas Daniel <davisthomasdaniel@gmail.com>, Josef Granwehr <j.granwehr@fz-juelich.de>
Maintainer-email: Davis Thomas Daniel <davisthomasdaniel@gmail.com>
License-Expression: LGPL-3.0-or-later
Project-URL: Homepage, https://apps.fz-juelich.de/iltpy
Project-URL: Documentation, https://apps.fz-juelich.de/iltpy
Project-URL: Repository, https://jugit.fz-juelich.de/iet-1/iltpy
Project-URL: Issues, https://jugit.fz-juelich.de/iet-1/iltpy/-/issues
Project-URL: Changelog, https://jugit.fz-juelich.de/iet-1/iltpy/-/blob/main/CHANGELOG
Keywords: EPR,NMR,DRT,Inverse Laplace transform,Laplace inversion,Relaxation,Impedance
Classifier: Development Status :: 5 - Production/Stable
Classifier: Programming Language :: Python :: 3
Classifier: Programming Language :: Python :: 3.9
Classifier: Programming Language :: Python :: 3.10
Classifier: Programming Language :: Python :: 3.11
Classifier: Programming Language :: Python :: 3.12
Classifier: Programming Language :: Python :: 3.13
Classifier: Intended Audience :: Science/Research
Classifier: Topic :: Scientific/Engineering :: Physics
Classifier: Topic :: Scientific/Engineering :: Chemistry
Classifier: Operating System :: Microsoft :: Windows
Classifier: Operating System :: MacOS
Classifier: Operating System :: POSIX :: Linux
Requires-Python: >=3.9, <3.14
License-File: LICENSE
License-File: COPYING.LESSER.txt
License-File: COPYING.txt
License-File: CITATION.cff
Requires-Dist: scipy<=1.16.0,>=1.13.1
Requires-Dist: numpy<=2.3.1,>1.25.1
Requires-Dist: joblib<=1.5.1,>=1.4.2
Requires-Dist: tqdm
Provides-Extra: develop
Requires-Dist: matplotlib; extra == "develop"
Requires-Dist: pytest; extra == "develop"
Requires-Dist: pytest-cov; extra == "develop"
Requires-Dist: sphinx; extra == "develop"
Requires-Dist: nbsphinx==0.9.5; extra == "develop"
Requires-Dist: sphinx_rtd_theme==3.0.1; extra == "develop"
Requires-Dist: sphinx-togglebutton==0.3.2; extra == "develop"
Requires-Dist: sphinx_design==0.6.1; extra == "develop"
Requires-Dist: sphinx-copybutton==0.5.2; extra == "develop"
Dynamic: author
Dynamic: home-page
Dynamic: license-file
Dynamic: requires-python
